{
    "name" : "irs.tax-rates.2025.json",
    "repository" : "https://github.com/bogle-tools/financial-figures",
    "path" : "data/usa/irs",
    "version" : "1.0.0",
    "note" : "DATA STRUCTURE AND FILE LOCATIONS STABLE",
    
    "source" : [
        { 
            "date" : "2024-10-22",
            "title" : "IRS IR-2024-273: IRS releases tax inflation adjustments for tax year 2025",
            "url" : "https://www.irs.gov/newsroom/irs-releases-tax-inflation-adjustments-for-tax-year-2025"
        },
        { 
            "date" : "2024-10-22",
            "title" : "IRS RP-2024-40: 26 CFR 601.602: Tax forms and instruction",
            "url" : "https://www.irs.gov/pub/irs-drop/rp-24-40.pdf"
        }
    ],
    "TaxData" : {
        "AnnualExclusionForGifts" : 19000,
        "TaxFilers" : [
            {
                "TaxFilingStatus" : "Single",
                "StandardDeduction" : 15750,
                "TaxBrackets" : [
                    { "Rate" : "10%", "StartAmount" : 0 },
                    { "Rate" : "12%", "StartAmount" : 11925 },
                    { "Rate" : "22%", "StartAmount" : 48475 },
                    { "Rate" : "24%", "StartAmount" : 103350 },
                    { "Rate" : "32%", "StartAmount" : 197300 },
                    { "Rate" : "35%", "StartAmount" : 250525 },
                    { "Rate" : "37%", "StartAmount" : 626350 }
                ]
            },
            {
                "TaxFilingStatus" : "MarriedFilingJointly",
                "StandardDeduction" : 31500,
                "TaxBrackets" : [
                    { "Rate" : "10%", "StartAmount" : 0 },
                    { "Rate" : "12%", "StartAmount" : 23850 },
                    { "Rate" : "22%", "StartAmount" : 96950 },
                    { "Rate" : "24%", "StartAmount" : 206700 },
                    { "Rate" : "32%", "StartAmount" : 394600 },
                    { "Rate" : "35%", "StartAmount" : 501050 },
                    { "Rate" : "37%", "StartAmount" : 751600 }
                ]
            },
            {
                "TaxFilingStatus" : "HeadOfHousehold",
                "StandardDeduction" : 23625,
                "TaxBrackets" : [
                    { "Rate" : "10%", "StartAmount" : 0 },
                    { "Rate" : "12%", "StartAmount" : 17000 },
                    { "Rate" : "22%", "StartAmount" : 64850 },
                    { "Rate" : "24%", "StartAmount" : 103350 },
                    { "Rate" : "32%", "StartAmount" : 197300 },
                    { "Rate" : "35%", "StartAmount" : 250525 },
                    { "Rate" : "37%", "StartAmount" : 626350 }
                ]
            },
            {
                "TaxFilingStatus" : "MarriedFilingSeperately",
                "StandardDeduction" : 15000,
                "TaxBrackets" : [
                    { "Rate" : "10%", "StartAmount" : 0 },
                    { "Rate" : "12%", "StartAmount" : 11925 },
                    { "Rate" : "22%", "StartAmount" : 48475 },
                    { "Rate" : "24%", "StartAmount" : 103350 },
                    { "Rate" : "32%", "StartAmount" : 197300 },
                    { "Rate" : "35%", "StartAmount" : 250525 },
                    { "Rate" : "37%", "StartAmount" : 375800 }
                ]
            },
            {
                "TaxFilingStatus" : "EstatesAndTrusts",
                "TaxBrackets" : [
                    { "Rate" : "10%", "StartAmount" : 0 },
                    { "Rate" : "24%", "StartAmount" : 3150 },
                    { "Rate" : "35%", "StartAmount" : 11450 },
                    { "Rate" : "37%", "StartAmount" : 15650 }
                ]
            }
        ]
    }
}